gasbullet/__init__.py
gasbullet/cache.py
gasbullet/filter.py
gasbullet/skeleton.py
gasbullet-0.0.22.dist-info/LICENSE.txt
gasbullet-0.0.22.dist-info/METADATA
gasbullet-0.0.22.dist-info/WHEEL
gasbullet-0.0.22.dist-info/entry_points.txt
gasbullet-0.0.22.dist-info/top_level.txt
gasbullet-0.0.22.dist-info/RECORD
