Metadata-Version: 2.1
Name: gasbullet
Version: 0.0.22
Summary: Add a short description here!
Home-page: https://github.com/pyscaffold/pyscaffold/
Author: Taylor Monacelli
Author-email: taylormonacelli@gmail.com
License: MPL-2.0
Project-URL: Documentation, https://pyscaffold.org/
Platform: any
Classifier: Development Status :: 4 - Beta
Classifier: Programming Language :: Python
License-File: LICENSE.txt
Requires-Dist: python-magic ; platform_system != "Windows"
Requires-Dist: python-magic-bin ; platform_system == "Windows"
Requires-Dist: importlib-metadata ; python_version < "3.8"
Provides-Extra: testing
Requires-Dist: setuptools ; extra == 'testing'
Requires-Dist: pytest ; extra == 'testing'
Requires-Dist: pytest-cov ; extra == 'testing'
Requires-Dist: black ; extra == 'testing'
